pysors/__init__.py
pysors/_minimize.py
pysors/ahds.py
pysors/bds.py
pysors/rs.py
pysors/rspi.py
pysors/stp.py
pysors/utils.py
pysors-1.0.0.dist-info/LICENSE
pysors-1.0.0.dist-info/METADATA
pysors-1.0.0.dist-info/WHEEL
pysors-1.0.0.dist-info/top_level.txt
pysors-1.0.0.dist-info/RECORD
