Metadata-Version: 2.1
Name: pysors
Version: 1.0.0
Summary: Fork of second-order-random-search with scipy.minimize-like interface.
Author-email: Ivan Nikishev <nkshv2@gmail.com>
License: Apache License
Project-URL: Homepage, https://github.com/inikishev/pySORS
Project-URL: Repository, https://github.com/inikishev/pySORS
Project-URL: Issues, https://github.com/inikishev/pySORS/isses
Keywords: optimization,optimizers,blackbox,black box,random search,second order
Requires-Python: >=3.9
License-File: LICENSE
Requires-Dist: numpy
